<PAMDataset>
  <Metadata>
    <MDI key="DataType">Generic</MDI>
  </Metadata>
  <PAMRasterBand band="1">
    <Description>Band_1</Description>
    <Histograms>
      <HistItem>
        <HistMin>1</HistMin>
        <HistMax>28</HistMax>
        <BucketCount>256</BucketCount>
        <IncludeOutOfRange>1</IncludeOutOfRange>
        <Approximate>0</Approximate>
        <HistCounts>2201|0|0|0|0|0|0|0|0|1789|0|0|0|0|0|0|0|0|4399|0|0|0|0|0|0|0|0|0|25845|0|0|0|0|0|0|0|0|0|0|0|0|0|0|0|0|0|0|525|0|0|0|0|0|0|0|0|0|0|0|0|0|0|0|0|0|0|0|0|0|0|0|0|0|0|0|0|0|0|0|0|0|0|0|0|0|917|0|0|0|0|0|0|0|0|0|0|0|0|0|0|0|0|0|0|0|0|0|0|0|0|0|0|0|194587|0|0|0|0|0|0|0|0|0|5192|0|0|0|0|0|0|0|0|0|0|0|0|0|0|0|0|0|0|15458|0|0|0|0|0|0|0|0|12829|0|0|0|0|0|0|0|0|0|0|0|0|0|0|0|0|0|0|0|0|0|0|0|0|0|0|0|0|0|0|0|0|0|0|0|0|0|0|0|0|0|0|0|0|0|0|0|0|0|0|0|0|0|0|0|0|0|0|0|0|0|0|0|0|0|0|0|0|0|0|0|0|0|0|0|2002|0|0|0|0|0|0|0|0|0|0|0|0|0|0|0|0|0|0|0|0|0|0|0|0|0|0|0|673</HistCounts>
      </HistItem>
    </Histograms>
    <Metadata>
      <MDI key="BandName">Band_1</MDI>
      <MDI key="RepresentationType">ATHEMATIC</MDI>
      <MDI key="STATISTICS_EXCLUDEDVALUES"></MDI>
      <MDI key="STATISTICS_MAXIMUM">28</MDI>
      <MDI key="STATISTICS_MEAN">12.278908628203</MDI>
      <MDI key="STATISTICS_MEDIAN">nan</MDI>
      <MDI key="STATISTICS_MINIMUM">1</MDI>
      <MDI key="STATISTICS_SKIPFACTORX">1</MDI>
      <MDI key="STATISTICS_SKIPFACTORY">1</MDI>
      <MDI key="STATISTICS_STDDEV">3.7525127286519</MDI>
    </Metadata>
  </PAMRasterBand>
</PAMDataset>
